Workbook

Sheet Cadastro Corretoras
A1: CADASTRO DE CORRETORAS — CLASSIFICAÇÃO POR PARTICIPANTE
A2: Corretora | B2: Categoria | C2: Descrição / Observação | D2: Ativa?
A3: Barclays | B3: Estrangeiro | C3: Banco britânico | D3: SIM
A4: BNP | B4: Estrangeiro | C4: BANCO BNP PARIBAS BRASIL S/A | D4: SIM
A5: Citibank | B5: Estrangeiro | C5: Citibank DTVM S.A. | D5: SIM
A6: Credit | B6: Estrangeiro | C6: CREDIT SUISSE BRASIL S.A. CTVM | D6: SIM
A7: Deutsche | B7: Estrangeiro | C7: DEUTSCHE BANK-CV S/A | D7: SIM
A8: Goldman | B8: Estrangeiro | C8: GOLDMAN SACHS DO BRASIL CTVM | D8: SIM
A9: HSBC | B9: Estrangeiro | C9: Banco britânico | D9: SIM
A10: JP Morgan | B10: Estrangeiro | C10: J. P. MORGAN CCVM S.A. | D10: SIM
A11: Macquarie | B11: Estrangeiro | C11: Banco australiano | D11: SIM
A12: Merrill | B12: Estrangeiro | C12: MERRILL LYNCH S/A CTVM | D12: SIM
A13: Morgan | B13: Estrangeiro | C13: MORGAN STANLEY CTVM S/A | D13: SIM
... A43: Goldman | B43: Outros | C43: GOLDMAN SACHS DO BRASIL CTVM | D43: SIM
A45: ⚠️ Edite a coluna 'Categoria' conforme necessário. Essa tabela é referenciada na aba 'Entrada de Dados'.

Sheet Dados a ser Importados
A2: DOLAR | H2: INDICE | Q2: ATIVO

Sheet Entrada de Dados
A1: ENTRADA DE DADOS — Cole aqui os dados do Profit Pro
A2: → Cole as colunas: Corretora | % | Vol. Financeiro | Vol. Qtd (separadas por Tab, direto do Excel do Profit Pro)
A3: Corretora | B3: % | C3: Vol. Financeiro (R$) | D3: Vol. Qtd | E3: Categoria | F3: Grupo Calc.
E4: =IFERROR(INDEX('Cadastro Corretoras'!$B$3:$B$43,MATCH(A4,'Cadastro Corretoras'!$A$3:$A$43,0)),"— não mapeada") -> — não mapeada | F4: =IF(E4="Estrangeiro","EXT",IF(E4="Institucional","INST",IF(E4="Pessoa Física","PF","OUT"))) -> OUT
E5: =IFERROR(INDEX('Cadastro Corretoras'!$B$3:$B$43,MATCH(A5,'Cadastro Corretoras'!$A$3:$A$43,0)),"— não mapeada") -> — não mapeada | F5: =IF(E5="Estrangeiro","EXT",IF(E5="Institucional","INST",IF(E5="Pessoa Física","PF","OUT"))) -> OUT
E6: =IFERROR(INDEX('Cadastro Corretoras'!$B$3:$B$43,MATCH(A6,'Cadastro Corretoras'!$A$3:$A$43,0)),"— não mapeada") -> — não mapeada | F6: =IF(E6="Estrangeiro","EXT",IF(E6="Institucional","INST",IF(E6="Pessoa Física","PF","OUT"))) -> OUT
E7: =IFERROR(INDEX('Cadastro Corretoras'!$B$3:$B$43,MATCH(A7,'Cadastro Corretoras'!$A$3:$A$43,0)),"— não mapeada") -> — não mapeada | F7: =IF(E7="Estrangeiro","EXT",IF(E7="Institucional","INST",IF(E7="Pessoa Física","PF","OUT"))) -> OUT
E8: =IFERROR(INDEX('Cadastro Corretoras'!$B$3:$B$43,MATCH(A8,'Cadastro Corretoras'!$A$3:$A$43,0)),"— não mapeada") -> — não mapeada | F8: =IF(E8="Estrangeiro","EXT",IF(E8="Institucional","INST",IF(E8="Pessoa Física","PF","OUT"))) -> OUT
E9: =IFERROR(INDEX('Cadastro Corretoras'!$B$3:$B$43,MATCH(A9,'Cadastro Corretoras'!$A$3:$A$43,0)),"— não mapeada") -> — não mapeada | F9: =IF(E9="Estrangeiro","EXT",IF(E9="Institucional","INST",IF(E9="Pessoa Física","PF","OUT"))) -> OUT
E10: =IFERROR(INDEX('Cadastro Corretoras'!$B$3:$B$43,MATCH(A10,'Cadastro Corretoras'!$A$3:$A$43,0)),"— não mapeada") -> — não mapeada | F10: =IF(E10="Estrangeiro","EXT",IF(E10="Institucional","INST",IF(E10="Pessoa Física","PF","OUT"))) -> OUT
E11: =IFERROR(INDEX('Cadastro Corretoras'!$B$3:$B$43,MATCH(A11,'Cadastro Corretoras'!$A$3:$A$43,0)),"— não mapeada") -> — não mapeada | F11: =IF(E11="Estrangeiro","EXT",IF(E11="Institucional","INST",IF(E11="Pessoa Física","PF","OUT"))) -> OUT
E12: =IFERROR(INDEX('Cadastro Corretoras'!$B$3:$B$43,MATCH(A12,'Cadastro Corretoras'!$A$3:$A$43,0)),"— não mapeada") -> — não mapeada | F12: =IF(E12="Estrangeiro","EXT",IF(E12="Institucional","INST",IF(E12="Pessoa Física","PF","OUT"))) -> OUT
E13: =IFERROR(INDEX('Cadastro Corretoras'!$B$3:$B$43,MATCH(A13,'Cadastro Corretoras'!$A$3:$A$43,0)),"— não mapeada") -> — não mapeada | F13: =IF(E13="Estrangeiro","EXT",IF(E13="Institucional","INST",IF(E13="Pessoa Física","PF","OUT"))) -> OUT
E14: =IFERROR(INDEX('Cadastro Corretoras'!$B$3:$B$43,MATCH(A14,'Cadastro Corretoras'!$A$3:$A$43,0)),"— não mapeada") -> — não mapeada | F14: =IF(E14="Estrangeiro","EXT",IF(E14="Institucional","INST",IF(E14="Pessoa Física","PF","OUT"))) -> OUT
E15: =IFERROR(INDEX('Cadastro Corretoras'!$B$3:$B$43,MATCH(A15,'Cadastro Corretoras'!$A$3:$A$43,0)),"— não mapeada") -> — não mapeada | F15: =IF(E15="Estrangeiro","EXT",IF(E15="Institucional","INST",IF(E15="Pessoa Física","PF","OUT"))) -> OUT
... E43: =IFERROR(INDEX('Cadastro Corretoras'!$B$3:$B$43,MATCH(A43,'Cadastro Corretoras'!$A$3:$A$43,0)),"— não mapeada") -> — não mapeada | F43: =IF(E43="Estrangeiro","EXT",IF(E43="Institucional","INST",IF(E43="Pessoa Física","PF","OUT"))) -> OUT

Sheet Resumo por Grupo
A1: RESUMO — FLUXO POR CATEGORIA DE PARTICIPANTE
A2: Categoria | B2: Compra (R$) | C2: Venda (R$) | D2: Saldo Líq. (R$) | E2: % do Total | F2: Posição | G2: _raw_compra | H2: _raw_venda | I2: _raw_saldo
A3: Estrangeiro | B3: =IF(ABS(G3)>=1000000000,"R$ "&TEXT(G3/1000000000,"0.00")&" B",IF(ABS(G3)>=1000000,"R$ "&TEXT(G3/1000000,"0.00")&" M",IF(ABS(G3)>=1000,"R$ "&TEXT(G3/1000,"0.00")&" K","R$ "&TEXT(G3,"#,##0")))) -> R$ ,0 | C3: =IF(ABS(H3)>=1000000000,"R$ "&TEXT(H3/1000000000,"0.00")&" B",IF(ABS(H3)>=1000000,"R$ "&TEXT(H3/1000000,"0.00")&" M",IF(ABS(H3)>=1000,"R$ "&TEXT(H3/1000,"0.00")&" K","R$ "&TEXT(H3,"#,##0")))) -> R$ ,0 | D3: =IF(ABS(I3)>=1000000000,"R$ "&TEXT(I3/1000000000,"0.00")&" B",IF(ABS(I3)>=1000000,"R$ "&TEXT(I3/1000000,"0.00")&" M",IF(ABS(I3)>=1000,"R$ "&TEXT(I3/1000,"0.00")&" K","R$ "&TEXT(I3,"#,##0")))) -> R$ ,0 | E3: =IFERROR(I3/ABS(SUM($I$3:$I$6)),0) -> 0 | F3: =IF(I3>0,"COMPRADO",IF(I3<0,"VENDIDO","NEUTRO")) -> NEUTRO | G3: =SUMPRODUCT(('Entrada de Dados'!F$4:F$43="EXT")*('Entrada de Dados'!C$4:C$43>0)*'Entrada de Dados'!C$4:C$43) -> 0 | H3: =SUMPRODUCT(('Entrada de Dados'!F$4:F$43="EXT")*('Entrada de Dados'!C$4:C$43<0)*'Entrada de Dados'!C$4:C$43) -> 0 | I3: =G3+H3 -> 0
A4: Institucional | B4: =IF(ABS(G4)>=1000000000,"R$ "&TEXT(G4/1000000000,"0.00")&" B",IF(ABS(G4)>=1000000,"R$ "&TEXT(G4/1000000,"0.00")&" M",IF(ABS(G4)>=1000,"R$ "&TEXT(G4/1000,"0.00")&" K","R$ "&TEXT(G4,"#,##0")))) -> R$ ,0 | C4: =IF(ABS(H4)>=1000000000,"R$ "&TEXT(H4/1000000000,"0.00")&" B",IF(ABS(H4)>=1000000,"R$ "&TEXT(H4/1000000,"0.00")&" M",IF(ABS(H4)>=1000,"R$ "&TEXT(H4/1000,"0.00")&" K","R$ "&TEXT(H4,"#,##0")))) -> R$ ,0 | D4: =IF(ABS(I4)>=1000000000,"R$ "&TEXT(I4/1000000000,"0.00")&" B",IF(ABS(I4)>=1000000,"R$ "&TEXT(I4/1000000,"0.00")&" M",IF(ABS(I4)>=1000,"R$ "&TEXT(I4/1000,"0.00")&" K","R$ "&TEXT(I4,"#,##0")))) -> R$ ,0 | E4: =IFERROR(I4/ABS(SUM($I$3:$I$6)),0) -> 0 | F4: =IF(I4>0,"COMPRADO",IF(I4<0,"VENDIDO","NEUTRO")) -> NEUTRO | G4: =SUMPRODUCT(('Entrada de Dados'!F$4:F$43="INST")*('Entrada de Dados'!C$4:C$43>0)*'Entrada de Dados'!C$4:C$43) -> 0 | H4: =SUMPRODUCT(('Entrada de Dados'!F$4:F$43="INST")*('Entrada de Dados'!C$4:C$43<0)*'Entrada de Dados'!C$4:C$43) -> 0 | I4: =G4+H4 -> 0
A5: Pessoa Física | B5: =IF(ABS(G5)>=1000000000,"R$ "&TEXT(G5/1000000000,"0.00")&" B",IF(ABS(G5)>=1000000,"R$ "&TEXT(G5/1000000,"0.00")&" M",IF(ABS(G5)>=1000,"R$ "&TEXT(G5/1000,"0.00")&" K","R$ "&TEXT(G5,"#,##0")))) -> R$ ,0 | C5: =IF(ABS(H5)>=1000000000,"R$ "&TEXT(H5/1000000000,"0.00")&" B",IF(ABS(H5)>=1000000,"R$ "&TEXT(H5/1000000,"0.00")&" M",IF(ABS(H5)>=1000,"R$ "&TEXT(H5/1000,"0.00")&" K","R$ "&TEXT(H5,"#,##0")))) -> R$ ,0 | D5: =IF(ABS(I5)>=1000000000,"R$ "&TEXT(I5/1000000000,"0.00")&" B",IF(ABS(I5)>=1000000,"R$ "&TEXT(I5/1000000,"0.00")&" M",IF(ABS(I5)>=1000,"R$ "&TEXT(I5/1000,"0.00")&" K","R$ "&TEXT(I5,"#,##0")))) -> R$ ,0 | E5: =IFERROR(I5/ABS(SUM($I$3:$I$6)),0) -> 0 | F5: =IF(I5>0,"COMPRADO",IF(I5<0,"VENDIDO","NEUTRO")) -> NEUTRO | G5: =SUMPRODUCT(('Entrada de Dados'!F$4:F$43="PF")*('Entrada de Dados'!C$4:C$43>0)*'Entrada de Dados'!C$4:C$43) -> 0 | H5: =SUMPRODUCT(('Entrada de Dados'!F$4:F$43="PF")*('Entrada de Dados'!C$4:C$43<0)*'Entrada de Dados'!C$4:C$43) -> 0 | I5: =G5+H5 -> 0
A6: Outros | B6: =IF(ABS(G6)>=1000000000,"R$ "&TEXT(G6/1000000000,"0.00")&" B",IF(ABS(G6)>=1000000,"R$ "&TEXT(G6/1000000,"0.00")&" M",IF(ABS(G6)>=1000,"R$ "&TEXT(G6/1000,"0.00")&" K","R$ "&TEXT(G6,"#,##0")))) -> R$ ,0 | C6: =IF(ABS(H6)>=1000000000,"R$ "&TEXT(H6/1000000000,"0.00")&" B",IF(ABS(H6)>=1000000,"R$ "&TEXT(H6/1000000,"0.00")&" M",IF(ABS(H6)>=1000,"R$ "&TEXT(H6/1000,"0.00")&" K","R$ "&TEXT(H6,"#,##0")))) -> R$ ,0 | D6: =IF(ABS(I6)>=1000000000,"R$ "&TEXT(I6/1000000000,"0.00")&" B",IF(ABS(I6)>=1000000,"R$ "&TEXT(I6/1000000,"0.00")&" M",IF(ABS(I6)>=1000,"R$ "&TEXT(I6/1000,"0.00")&" K","R$ "&TEXT(I6,"#,##0")))) -> R$ ,0 | E6: =IFERROR(I6/ABS(SUM($I$3:$I$6)),0) -> 0 | F6: =IF(I6>0,"COMPRADO",IF(I6<0,"VENDIDO","NEUTRO")) -> NEUTRO | G6: =SUMPRODUCT(('Entrada de Dados'!F$4:F$43="OUT")*('Entrada de Dados'!C$4:C$43>0)*'Entrada de Dados'!C$4:C$43) -> 0 | H6: =SUMPRODUCT(('Entrada de Dados'!F$4:F$43="OUT")*('Entrada de Dados'!C$4:C$43<0)*'Entrada de Dados'!C$4:C$43) -> 0 | I6: =G6+H6 -> 0
A8: ℹ️ Os valores acima são calculados automaticamente a partir da aba 'Entrada de Dados'. Cole os dados do Profit Pro naquela aba e volte aqui para ver o resumo.
